MANIFEST.in
setup.py
lightpivot2/__init__.py
lightpivot2/pivot.cpython-36m-x86_64-linux-gnu.so
lightpivot2.egg-info/PKG-INFO
lightpivot2.egg-info/SOURCES.txt
lightpivot2.egg-info/dependency_links.txt
lightpivot2.egg-info/not-zip-safe
lightpivot2.egg-info/top_level.txt