Metadata-Version: 1.0
Name: lightpivot2
Version: 0.2.1
Summary: light pivot feature engineer
Home-page: http://github.com/fe/lightpivot2
Author: fefly
Author-email: fefly@gmail.com
License: MIT
Platform: UNKNOWN
